number-theory/__init__.py
number-theory/common_functions.py
number-theory/fibonacci.py
number-theory/generating_primes.py
number-theory/integer_factorization.py
number-theory/modulus_operations.py
number-theory/primality_tests.py
numbertheory/__init__.py
numbertheory/common_functions.py
numbertheory/discrete-log-problem.py
numbertheory/elliptic_curves.py
numbertheory/fibonacci.py
numbertheory/generating_primes.py
numbertheory/integer_factorization.py
numbertheory/modulus_operations.py
numbertheory/primality_tests.py
numbertheory-0.0.4.dist-info/METADATA
numbertheory-0.0.4.dist-info/WHEEL
numbertheory-0.0.4.dist-info/top_level.txt
numbertheory-0.0.4.dist-info/RECORD
