Metadata-Version: 2.1
Name: numbertheory
Version: 0.0.4
Summary: Common number theoretic functions.
Home-page: https://0xkilty.github.io/number-theory/
Author: 0xKilty
Author-email: ian.kilty@colostate.edu
License: MIT
Classifier: License :: OSI Approved :: MIT License
Classifier: Operating System :: OS Independent
Classifier: Programming Language :: Python
Classifier: Topic :: Software Development :: Libraries :: Python Modules
Classifier: Intended Audience :: Developers
Classifier: Natural Language :: English
Provides-Extra: dev
Requires-Dist: twine >=4.0.2 ; extra == 'dev'
